{
	"name": "Bedroom2",
	"events": [
		{
			"eventType": "include",
			"includeSheet": "Global"
		},
		{
			"eventType": "block",
			"conditions": [
				{
					"id": "on-start-of-layout",
					"objectClass": "System",
					"sid": 661957235695102
				}
			],
			"actions": [
				{
					"callFunction": "destroyDialogue",
					"sid": 725090180425704
				},
				{
					"callFunction": "dialogue",
					"sid": 917658015513363,
					"parameters": [
						"\"Opal: Hmm... Maybe I should go to the laptop and work... \""
					]
				},
				{
					"id": "wait",
					"objectClass": "System",
					"sid": 999150138919198,
					"parameters": {
						"seconds": "2",
						"use-timescale": true
					}
				},
				{
					"callFunction": "destroyDialogue",
					"sid": 112983592188533
				}
			],
			"sid": 573558558804685
		},
		{
			"eventType": "block",
			"conditions": [
				{
					"id": "on-key-pressed",
					"objectClass": "Keyboard",
					"sid": 616216943808839,
					"parameters": {
						"key": 69
					}
				},
				{
					"id": "every-tick",
					"objectClass": "System",
					"sid": 921931157391381
				},
				{
					"id": "is-overlapping-another-object",
					"objectClass": "PlayerMovement",
					"sid": 856984063416219,
					"parameters": {
						"object": "StartBoxes"
					}
				}
			],
			"actions": [
				{
					"type": "script",
					"language": "typescript",
					"script": [
						"updateState(State.MgMemoryBegin)"
					]
				}
			],
			"sid": 870464386371177
		},
		{
			"eventType": "block",
			"conditions": [
				{
					"id": "every-tick",
					"objectClass": "System",
					"sid": 620360366601764
				},
				{
					"id": "is-overlapping-another-object",
					"objectClass": "PlayerMovement",
					"sid": 465921891324072,
					"parameters": {
						"object": "StartBoxes"
					}
				}
			],
			"actions": [
				{
					"id": "set-animation",
					"objectClass": "laptoptypeshiiiii",
					"sid": 200473393188908,
					"parameters": {
						"animation": "\"lit\"",
						"from": "beginning"
					}
				}
			],
			"sid": 907641302236034
		},
		{
			"eventType": "block",
			"conditions": [
				{
					"id": "else",
					"objectClass": "System",
					"sid": 467580413646148
				}
			],
			"actions": [
				{
					"id": "set-animation",
					"objectClass": "laptoptypeshiiiii",
					"sid": 940101764055566,
					"parameters": {
						"animation": "\"normal\"",
						"from": "beginning"
					}
				}
			],
			"sid": 582815389491871
		},
		{
			"eventType": "block",
			"conditions": [
				{
					"id": "on-key-pressed",
					"objectClass": "Keyboard",
					"sid": 335797628312585,
					"parameters": {
						"key": 69
					}
				},
				{
					"id": "every-tick",
					"objectClass": "System",
					"sid": 866929503331096
				},
				{
					"id": "is-overlapping-another-object",
					"objectClass": "PlayerMovement",
					"sid": 427989599361230,
					"parameters": {
						"object": "SwitchRoom"
					}
				}
			],
			"actions": [
				{
					"id": "go-to-layout-by-name",
					"objectClass": "System",
					"sid": 680090210409768,
					"parameters": {
						"layout": "\"Outside_bedroom\""
					}
				}
			],
			"sid": 142343867976408
		}
	],
	"sid": 203754346391334
}